securemcrcon/__init__.py
securemcrcon/__main__.py
securemcrcon/main.py
securemcrcon/cli/argParser.py
securemcrcon/cli/keyManager.py
securemcrcon/client/__init__.py
securemcrcon/client/encryptedRCON.py
securemcrcon/client/legacyRCON.py
securemcrcon/utils/encrypt.py
securemcrcon/utils/exchange.py
securemcrcon/utils/packet.py
securemcrcon-0.0.3.dist-info/licenses/LICENSE
securemcrcon-0.0.3.dist-info/METADATA
securemcrcon-0.0.3.dist-info/WHEEL
securemcrcon-0.0.3.dist-info/entry_points.txt
securemcrcon-0.0.3.dist-info/top_level.txt
securemcrcon-0.0.3.dist-info/RECORD
