Metadata-Version: 2.4
Name: securemcrcon
Version: 0.0.3
Summary: A RCON protocol client for Minecraft RCON and my SecureRCON protocol
Author-email: wangyupu <me@wytl.cc>
License: MIT
Project-URL: Homepage, https://github.com/wang-yupu/SecureMCRCON
Requires-Python: >=3.10
License-File: LICENSE
Requires-Dist: prompt_toolkit>=3.0.0
Requires-Dist: cryptography>=40.0.0
Dynamic: license-file
